AUTHORS.rst
CONTRIBUTING.rst
HISTORY.rst
LICENSE
MANIFEST.in
README.rst
setup.cfg
setup.py
docs/Makefile
docs/authors.rst
docs/conf.py
docs/contributing.rst
docs/history.rst
docs/index.rst
docs/installation.rst
docs/make.bat
docs/readme.rst
docs/usage.rst
fabian/__init__.py
fabian/cron.py
fabian/fabian.py
fabian.egg-info/PKG-INFO
fabian.egg-info/SOURCES.txt
fabian.egg-info/dependency_links.txt
fabian.egg-info/not-zip-safe
fabian.egg-info/requires.txt
fabian.egg-info/top_level.txt
fabian/contrib/__init__.py
fabian/contrib/crontabs.py
fabian/contrib/klaus.py
fabian/contrib/redmine.py
fabian/contrib/s3.py
fabian/contrib/s3cfg.conf.template
fabian/contrib/sentry.conf.template
fabian/contrib/sentry.py
fabian/templates/__init__.py
fabian/templates/nginx.conf.template
fabian/templates/supervisor_app.conf.template
tests/__init__.py
tests/test_fabian.py