Metadata-Version: 1.1
Name: fabian
Version: 0.1.0
Summary: Fabian is a set of common functions useful for installing webapps on Debian machines using fabric
Home-page: https://tracker.ajenta.net/projects/fabian
Author: Luke Drummond
Author-email: luke@ajenta.net
License: BSD
Keywords: fabian
Platform: UNKNOWN
Classifier: Development Status :: 2 - Pre-Alpha
Classifier: Intended Audience :: Developers
Classifier: License :: OSI Approved :: BSD License
Classifier: Natural Language :: English
Classifier: Programming Language :: Python :: 2
Classifier: Programming Language :: Python :: 2.6
Classifier: Programming Language :: Python :: 2.7
